CHANGELOG.rst
LICENSE
MANIFEST.in
README.rst
setup.py
tests/__init__.py
tests/test_cli.py
tests/test_client.py
tests/test_items.py
tests/spiders/__init__.py
tests/spiders/_common.py
tests/spiders/test_idope.py
tests/spiders/test_limetorrents.py
tests/spiders/test_onethreethreesevenx.py
tests/spiders/test_skytorrents.py
tests/spiders/test_thepiratebay.py
tests/spiders/test_torlock.py
tests/spiders/test_torrentz2.py
torvend/__init__.py
torvend/__main__.py
torvend/__version__.py
torvend/cli.py
torvend/client.py
torvend/const.py
torvend/items.py
torvend.egg-info/PKG-INFO
torvend.egg-info/SOURCES.txt
torvend.egg-info/dependency_links.txt
torvend.egg-info/entry_points.txt
torvend.egg-info/requires.txt
torvend.egg-info/top_level.txt
torvend/meta/__init__.py
torvend/meta/loggable.py
torvend/spiders/__init__.py
torvend/spiders/_common.py
torvend/spiders/idope.py
torvend/spiders/limetorrents.py
torvend/spiders/onethreethreesevenx.py
torvend/spiders/rarbg.py
torvend/spiders/skytorrents.py
torvend/spiders/thepiratebay.py
torvend/spiders/torlock.py
torvend/spiders/torrentz2.py