Metadata-Version: 1.2
Name: torvend
Version: 0.0.0
Summary: A framework for public torrent vendor scrapers
Home-page: https://github.com/stephen-bunn/torvend
Author: Stephen Bunn
Author-email: stephen@bunn.io
License: MIT License
Keywords: web-scraping,torrent,search,python3,asynchronous,command-line,framework
Platform: UNKNOWN
Classifier: Development Status :: 2 - Pre-Alpha
Classifier: Programming Language :: Python :: 3.5
Classifier: Programming Language :: Python :: 3.6
Classifier: License :: OSI Approved :: MIT License
Classifier: Intended Audience :: Developers
Classifier: Intended Audience :: System Administrators
Classifier: Operating System :: POSIX
Classifier: Operating System :: MacOS :: MacOS X
Classifier: Natural Language :: English
Classifier: Topic :: Internet :: WWW/HTTP :: Indexing/Search
Classifier: Topic :: Utilities
Requires-Python: >=3.5
